opsdata_sulphur_peak/__init__.py
opsdata_sulphur_peak/core.py
opsdata_sulphur_peak/version.py
opsdata_sulphur_peak-0.1.0.dist-info/LICENSE
opsdata_sulphur_peak-0.1.0.dist-info/METADATA
opsdata_sulphur_peak-0.1.0.dist-info/WHEEL
opsdata_sulphur_peak-0.1.0.dist-info/entry_points.txt
opsdata_sulphur_peak-0.1.0.dist-info/top_level.txt
opsdata_sulphur_peak-0.1.0.dist-info/RECORD
