Metadata-Version: 2.1
Name: opsdata-sulphur-peak
Version: 0.1.0
Summary: A 2017 earthquake sequence occurring in southern Idaho
Home-page: https://github.com/d-chambers/opsdata_sulphur_peak
Author: Derrick Chambers
Author-email: d-chambers@github.com
License: BSD
Platform: UNKNOWN
Classifier: Development Status :: 2 - Pre-Alpha
Classifier: Intended Audience :: Developers
Classifier: Natural Language :: English
Classifier: Programming Language :: Python :: 3.6
Classifier: Programming Language :: Python :: 3.7
